{"put_cargos": [], "cargo_space": {"id": 156864, "mass": 20, "size": [1250, 2100, 1800], "params": {"protrusion": [50, 50], "indentation": [50, 50]}, "carrying_capacity": 520}, "cargo_groups": [{"id": "56060Y1", "mass": 8712, "size": [260, 283, 200], "sort": 1, "count": 1, "stacking": true, "turnover": false, "overhang_angle": 50, "stacking_limit": 0, "stacking_is_limited": false, "group_id": "910102910G3"}, {"id": "54082Y1", "mass": 5698, "size": [320, 129, 240], "sort": 2, "count": 2, "stacking": true, "turnover": false, "overhang_angle": 50, "stacking_limit": 0, "stacking_is_limited": false, "group_id": "537770Z1"}, {"id": "54034Y1", "mass": 5609, "size": [310, 115, 230], "sort": 3, "count": 1, "stacking": true, "turnover": false, "overhang_angle": 50, "stacking_limit": 0, "stacking_is_limited": false, "group_id": "3101046F1"}, {"id": "54028Y1", "mass": 2648, "size": [270, 104, 140], "sort": 4, "count": 2, "stacking": true, "turnover": false, "overhang_angle": 50, "stacking_limit": 0, "stacking_is_limited": false, "group_id": "7610207F10"}, {"id": "53044Y1", "mass": 3275, "size": [280, 124, 150], "sort": 5, "count": 1, "stacking": true, "turnover": false, "overhang_angle": 50, "stacking_limit": 0, "stacking_is_limited": false, "group_id": "1060573R10"}, {"id": "45037Y1", "mass": 1918, "size": [370, 220, 300], "sort": 6, "count": 1, "stacking": true, "turnover": false, "overhang_angle": 50, "stacking_limit": 0, "stacking_is_limited": false, "group_id": "532573E1"}, {"id": "44081Y1", "mass": 3120, "size": [450, 151, 100], "sort": 7, "count": 1, "stacking": true, "turnover": false, "overhang_angle": 50, "stacking_limit": 0, "stacking_is_limited": false, "group_id": "863847B0"}, {"id": "26009Y1", "mass": 5043, "size": [160, 361, 130], "sort": 8, "count": 3, "stacking": true, "turnover": false, "overhang_angle": 50, "stacking_limit": 0, "stacking_is_limited": false, "group_id": "783942N0"}, {"id": "26005Y1", "mass": 10189, "size": [300, 340, 160], "sort": 9, "count": 1, "stacking": true, "turnover": false, "overhang_angle": 50, "stacking_limit": 0, "stacking_is_limited": false, "group_id": "287552E4"}, {"id": "26003Y1", "mass": 10139, "size": [310, 343, 140], "sort": 10, "count": 1, "stacking": true, "turnover": true, "overhang_angle": 50, "stacking_limit": 0, "stacking_is_limited": false, "group_id": "842757V2"}, {"id": "25010Y1", "mass": 4200, "size": [320, 99, 220], "sort": 11, "count": 4, "stacking": true, "turnover": false, "overhang_angle": 50, "stacking_limit": 0, "stacking_is_limited": false, "group_id": "361010101V7"}, {"id": "25013Y1", "mass": 5308, "size": [280, 203, 190], "sort": 12, "count": 1, "stacking": true, "turnover": false, "overhang_angle": 50, "stacking_limit": 0, "stacking_is_limited": false, "group_id": "3103983U1"}, {"id": "25091Y1", "mass": 6105, "size": [360, 88, 270], "sort": 13, "count": 2, "stacking": true, "turnover": false, "overhang_angle": 50, "stacking_limit": 0, "stacking_is_limited": false, "group_id": "4100697R4"}, {"id": "25111Y1", "mass": 3372, "size": [300, 137, 220], "sort": 14, "count": 1, "stacking": true, "turnover": false, "overhang_angle": 50, "stacking_limit": 0, "stacking_is_limited": false, "group_id": "022524H3"}, {"id": "25122Y1", "mass": 4181, "size": [210, 228, 190], "sort": 15, "count": 1, "stacking": true, "turnover": true, "overhang_angle": 50, "stacking_limit": 0, "stacking_is_limited": false, "group_id": "1410963D8"}, {"id": "25125Y1", "mass": 7905, "size": [350, 127, 260], "sort": 16, "count": 2, "stacking": true, "turnover": false, "overhang_angle": 50, "stacking_limit": 0, "stacking_is_limited": false, "group_id": "1093319F3"}, {"id": "25130Y1", "mass": 4893, "size": [350, 88, 270], "sort": 17, "count": 1, "stacking": true, "turnover": false, "overhang_angle": 50, "stacking_limit": 0, "stacking_is_limited": false, "group_id": "958783Y0"}, {"id": "24128Y1", "mass": 7093, "size": [360, 169, 190], "sort": 18, "count": 1, "stacking": true, "turnover": false, "overhang_angle": 50, "stacking_limit": 0, "stacking_is_limited": false, "group_id": "618274A4"}, {"id": "24122Y1", "mass": 7008, "size": [360, 172, 180], "sort": 19, "count": 1, "stacking": true, "turnover": false, "overhang_angle": 50, "stacking_limit": 0, "stacking_is_limited": false, "group_id": "189211C1"}, {"id": "24120Y1", "mass": 7618, "size": [210, 233, 210], "sort": 20, "count": 1, "stacking": true, "turnover": false, "overhang_angle": 50, "stacking_limit": 0, "stacking_is_limited": false, "group_id": "2410227K9"}, {"id": "24119Y1", "mass": 2706, "size": [270, 104, 150], "sort": 21, "count": 1, "stacking": true, "turnover": false, "overhang_angle": 50, "stacking_limit": 0, "stacking_is_limited": false, "group_id": "586631E5"}, {"id": "24086Y1", "mass": 4780, "size": [260, 160, 170], "sort": 22, "count": 1, "stacking": true, "turnover": true, "overhang_angle": 50, "stacking_limit": 0, "stacking_is_limited": false, "group_id": "333647P0"}, {"id": "24030Y1", "mass": 5215, "size": [260, 226, 220], "sort": 23, "count": 1, "stacking": true, "turnover": false, "overhang_angle": 50, "stacking_limit": 0, "stacking_is_limited": false, "group_id": "4231102M1"}, {"id": "24023Y1", "mass": 14050, "size": [400, 181, 290], "sort": 24, "count": 1, "stacking": true, "turnover": false, "overhang_angle": 50, "stacking_limit": 0, "stacking_is_limited": false, "group_id": "381414L10"}, {"id": "24008Y1", "mass": 10095, "size": [360, 130, 270], "sort": 25, "count": 1, "stacking": true, "turnover": false, "overhang_angle": 50, "stacking_limit": 0, "stacking_is_limited": false, "group_id": "802154Z10"}, {"id": "24001Y1", "mass": 3499, "size": [270, 182, 190], "sort": 26, "count": 1, "stacking": true, "turnover": true, "overhang_angle": 50, "stacking_limit": 0, "stacking_is_limited": false, "group_id": "608323Q3"}, {"id": "23024Y1", "mass": 8461, "size": [300, 360, 240], "sort": 27, "count": 1, "stacking": true, "turnover": false, "overhang_angle": 50, "stacking_limit": 0, "stacking_is_limited": false, "group_id": "794116X8"}, {"id": "23028Y1", "mass": 9535, "size": [390, 296, 300], "sort": 28, "count": 1, "stacking": true, "turnover": false, "overhang_angle": 50, "stacking_limit": 0, "stacking_is_limited": false, "group_id": "7010574J4"}, {"id": "23037Y1", "mass": 2170, "size": [400, 148, 100], "sort": 29, "count": 1, "stacking": true, "turnover": false, "overhang_angle": 50, "stacking_limit": 0, "stacking_is_limited": false, "group_id": "059589H3"}, {"id": "23040Y1", "mass": 468, "size": [190, 177, 120], "sort": 30, "count": 1, "stacking": true, "turnover": false, "overhang_angle": 50, "stacking_limit": 0, "stacking_is_limited": false, "group_id": "435114C2"}, {"id": "23085Y1", "mass": 2614, "size": [390, 144, 100], "sort": 31, "count": 1, "stacking": true, "turnover": false, "overhang_angle": 50, "stacking_limit": 0, "stacking_is_limited": false, "group_id": "306970W4"}, {"id": "23089Y1", "mass": 2213, "size": [400, 149, 110], "sort": 32, "count": 1, "stacking": true, "turnover": false, "overhang_angle": 50, "stacking_limit": 0, "stacking_is_limited": false, "group_id": "6420210E4"}, {"id": "23092Y1", "mass": 2170, "size": [400, 148, 100], "sort": 33, "count": 1, "stacking": true, "turnover": false, "overhang_angle": 50, "stacking_limit": 0, "stacking_is_limited": false, "group_id": "508629G8"}, {"id": "23100Y1", "mass": 3426, "size": [380, 264, 170], "sort": 34, "count": 1, "stacking": true, "turnover": false, "overhang_angle": 50, "stacking_limit": 0, "stacking_is_limited": false, "group_id": "1043380V4"}, {"id": "23121Y1", "mass": 3612, "size": [350, 100, 130], "sort": 35, "count": 1, "stacking": true, "turnover": false, "overhang_angle": 50, "stacking_limit": 0, "stacking_is_limited": false, "group_id": "595541F0"}, {"id": "22118Y1", "mass": 10858, "size": [300, 163, 270], "sort": 36, "count": 1, "stacking": true, "turnover": false, "overhang_angle": 50, "stacking_limit": 0, "stacking_is_limited": false, "group_id": "1018229I5"}, {"id": "22047Y1", "mass": 9424, "size": [210, 168, 360], "sort": 37, "count": 1, "stacking": true, "turnover": false, "overhang_angle": 50, "stacking_limit": 0, "stacking_is_limited": false, "group_id": "963901X9"}, {"id": "22043Y1", "mass": 1194, "size": [200, 74, 140], "sort": 38, "count": 1, "stacking": true, "turnover": false, "overhang_angle": 50, "stacking_limit": 0, "stacking_is_limited": false, "group_id": "5510607T9"}, {"id": "22042Y1", "mass": 10847, "size": [430, 99, 330], "sort": 39, "count": 1, "stacking": true, "turnover": true, "overhang_angle": 50, "stacking_limit": 0, "stacking_is_limited": false, "group_id": "422224W1"}, {"id": "22018Y1", "mass": 9080, "size": [220, 230, 240], "sort": 40, "count": 1, "stacking": true, "turnover": false, "overhang_angle": 50, "stacking_limit": 0, "stacking_is_limited": false, "group_id": "909576M3"}, {"id": "22009Y1", "mass": 288, "size": [400, 144, 100], "sort": 41, "count": 1, "stacking": true, "turnover": false, "overhang_angle": 50, "stacking_limit": 0, "stacking_is_limited": false, "group_id": "295224B6"}, {"id": "21094Y1", "mass": 9932, "size": [560, 207, 220], "sort": 42, "count": 1, "stacking": true, "turnover": false, "overhang_angle": 50, "stacking_limit": 0, "stacking_is_limited": false, "group_id": "1037335D0"}, {"id": "20131Y1", "mass": 2559, "size": [390, 150, 130], "sort": 43, "count": 1, "stacking": true, "turnover": false, "overhang_angle": 50, "stacking_limit": 0, "stacking_is_limited": false, "group_id": "249931R8"}, {"id": "20124Y1", "mass": 9534, "size": [550, 233, 280], "sort": 44, "count": 1, "stacking": true, "turnover": false, "overhang_angle": 50, "stacking_limit": 0, "stacking_is_limited": false, "group_id": "46105108T9"}, {"id": "20122Y1", "mass": 9452, "size": [360, 174, 210], "sort": 45, "count": 2, "stacking": true, "turnover": false, "overhang_angle": 50, "stacking_limit": 0, "stacking_is_limited": false, "group_id": "3881029Y0"}, {"id": "20082Y1", "mass": 4208, "size": [390, 143, 270], "sort": 46, "count": 1, "stacking": true, "turnover": false, "overhang_angle": 50, "stacking_limit": 0, "stacking_is_limited": false, "group_id": "2100697B7"}, {"id": "20053Y1", "mass": 3180, "size": [280, 168, 270], "sort": 47, "count": 1, "stacking": true, "turnover": false, "overhang_angle": 50, "stacking_limit": 0, "stacking_is_limited": false, "group_id": "10071074R3"}, {"id": "19026Y1", "mass": 3310, "size": [410, 187, 210], "sort": 48, "count": 2, "stacking": true, "turnover": false, "overhang_angle": 50, "stacking_limit": 0, "stacking_is_limited": false, "group_id": "1025667L9"}, {"id": "19074Y1", "mass": 3076, "size": [370, 134, 310], "sort": 49, "count": 1, "stacking": true, "turnover": false, "overhang_angle": 50, "stacking_limit": 0, "stacking_is_limited": false, "group_id": "4101380S0"}, {"id": "19124Y1", "mass": 2460, "size": [390, 142, 100], "sort": 50, "count": 1, "stacking": true, "turnover": false, "overhang_angle": 50, "stacking_limit": 0, "stacking_is_limited": false, "group_id": "532113P4"}, {"id": "18110Y1", "mass": 3615, "size": [340, 116, 310], "sort": 51, "count": 1, "stacking": true, "turnover": false, "overhang_angle": 50, "stacking_limit": 0, "stacking_is_limited": false, "group_id": "866869I1"}, {"id": "18031Y1", "mass": 4657, "size": [400, 258, 320], "sort": 52, "count": 1, "stacking": true, "turnover": true, "overhang_angle": 50, "stacking_limit": 0, "stacking_is_limited": false, "group_id": "880617U3"}, {"id": "17025Y1", "mass": 3756, "size": [300, 101, 200], "sort": 53, "count": 1, "stacking": true, "turnover": true, "overhang_angle": 50, "stacking_limit": 0, "stacking_is_limited": false, "group_id": "391010910I10"}, {"id": "17050Y1", "mass": 2237, "size": [390, 171, 300], "sort": 54, "count": 1, "stacking": true, "turnover": false, "overhang_angle": 50, "stacking_limit": 0, "stacking_is_limited": false, "group_id": "907972N9"}, {"id": "16009Y1", "mass": 1333, "size": [400, 152, 210], "sort": 55, "count": 1, "stacking": true, "turnover": false, "overhang_angle": 50, "stacking_limit": 0, "stacking_is_limited": false, "group_id": "1033308L5"}, {"id": "15029Y1", "mass": 6065, "size": [370, 133, 170], "sort": 56, "count": 1, "stacking": true, "turnover": true, "overhang_angle": 50, "stacking_limit": 0, "stacking_is_limited": false, "group_id": "024051H2"}, {"id": "14131Y1", "mass": 3280, "size": [530, 206, 240], "sort": 57, "count": 1, "stacking": true, "turnover": false, "overhang_angle": 50, "stacking_limit": 0, "stacking_is_limited": false, "group_id": "933966Y9"}, {"id": "14118Y1", "mass": 3387, "size": [330, 247, 120], "sort": 58, "count": 1, "stacking": true, "turnover": true, "overhang_angle": 50, "stacking_limit": 0, "stacking_is_limited": false, "group_id": "1651011O5"}, {"id": "14110Y1", "mass": 1742, "size": [390, 236, 180], "sort": 59, "count": 1, "stacking": true, "turnover": false, "overhang_angle": 50, "stacking_limit": 0, "stacking_is_limited": false, "group_id": "618273P8"}, {"id": "14096Y1", "mass": 448, "size": [270, 128, 140], "sort": 60, "count": 1, "stacking": true, "turnover": false, "overhang_angle": 50, "stacking_limit": 0, "stacking_is_limited": false, "group_id": "055116F2"}, {"id": "14050Y1", "mass": 442, "size": [260, 87, 200], "sort": 61, "count": 1, "stacking": true, "turnover": false, "overhang_angle": 50, "stacking_limit": 0, "stacking_is_limited": false, "group_id": "629059E5"}, {"id": "14049Y1", "mass": 442, "size": [180, 180, 220], "sort": 62, "count": 1, "stacking": true, "turnover": false, "overhang_angle": 50, "stacking_limit": 0, "stacking_is_limited": false, "group_id": "95106810P10"}, {"id": "14046Y1", "mass": 2434, "size": [390, 157, 80], "sort": 63, "count": 1, "stacking": true, "turnover": true, "overhang_angle": 50, "stacking_limit": 0, "stacking_is_limited": false, "group_id": "71087105W3"}, {"id": "13021Y1", "mass": 5371, "size": [410, 140, 210], "sort": 64, "count": 1, "stacking": true, "turnover": false, "overhang_angle": 50, "stacking_limit": 0, "stacking_is_limited": false, "group_id": "568968J4"}, {"id": "13061Y1", "mass": 1000, "size": [350, 151, 180], "sort": 65, "count": 1, "stacking": true, "turnover": false, "overhang_angle": 50, "stacking_limit": 0, "stacking_is_limited": false, "group_id": "1070653S0"}, {"id": "13089Y1", "mass": 2044, "size": [290, 186, 250], "sort": 66, "count": 1, "stacking": true, "turnover": false, "overhang_angle": 50, "stacking_limit": 0, "stacking_is_limited": false, "group_id": "8211040H3"}, {"id": "12026Y1", "mass": 2356, "size": [500, 268, 210], "sort": 67, "count": 1, "stacking": true, "turnover": false, "overhang_angle": 50, "stacking_limit": 0, "stacking_is_limited": false, "group_id": "4107932L0"}, {"id": "11081Y1", "mass": 2037, "size": [370, 173, 140], "sort": 68, "count": 1, "stacking": true, "turnover": false, "overhang_angle": 50, "stacking_limit": 0, "stacking_is_limited": false, "group_id": "488097S7"}, {"id": "11086Y1", "mass": 2100, "size": [350, 160, 120], "sort": 69, "count": 1, "stacking": true, "turnover": false, "overhang_angle": 50, "stacking_limit": 0, "stacking_is_limited": false, "group_id": "009484Q0"}, {"id": "11105Y1", "mass": 285, "size": [200, 114, 90], "sort": 70, "count": 1, "stacking": true, "turnover": false, "overhang_angle": 50, "stacking_limit": 0, "stacking_is_limited": false, "group_id": "056757A0"}, {"id": "10112Y1", "mass": 1510, "size": [460, 210, 180], "sort": 71, "count": 1, "stacking": true, "turnover": false, "overhang_angle": 50, "stacking_limit": 0, "stacking_is_limited": false, "group_id": "8109261S7"}, {"id": "10104Y1", "mass": 1194, "size": [310, 150, 240], "sort": 72, "count": 1, "stacking": true, "turnover": false, "overhang_angle": 50, "stacking_limit": 0, "stacking_is_limited": false, "group_id": "389706V5"}, {"id": "10088Y1", "mass": 2877, "size": [590, 200, 410], "sort": 73, "count": 1, "stacking": true, "turnover": false, "overhang_angle": 50, "stacking_limit": 0, "stacking_is_limited": false, "group_id": "0101031I2"}, {"id": "10050Y1", "mass": 451, "size": [450, 320, 320], "sort": 74, "count": 1, "stacking": true, "turnover": false, "overhang_angle": 50, "stacking_limit": 0, "stacking_is_limited": false, "group_id": "604455D1"}, {"id": "10042Y1", "mass": 303, "size": [510, 200, 270], "sort": 75, "count": 1, "stacking": true, "turnover": false, "overhang_angle": 50, "stacking_limit": 0, "stacking_is_limited": false, "group_id": "467883Q0"}, {"id": "10040Y1", "mass": 165, "size": [430, 160, 280], "sort": 76, "count": 1, "stacking": true, "turnover": false, "overhang_angle": 50, "stacking_limit": 0, "stacking_is_limited": false, "group_id": "3210644G1"}, {"id": "10039Y1", "mass": 566, "size": [240, 160, 190], "sort": 77, "count": 1, "stacking": true, "turnover": false, "overhang_angle": 50, "stacking_limit": 0, "stacking_is_limited": false, "group_id": "10010264R6"}, {"id": "10029Y1", "mass": 338, "size": [600, 310, 410], "sort": 78, "count": 1, "stacking": true, "turnover": false, "overhang_angle": 50, "stacking_limit": 0, "stacking_is_limited": false, "group_id": "991902A3"}, {"id": "10014Y1", "mass": 230, "size": [720, 30, 100], "sort": 79, "count": 1, "stacking": true, "turnover": false, "overhang_angle": 50, "stacking_limit": 0, "stacking_is_limited": false, "group_id": "640336I5"}, {"id": "10011Y1", "mass": 327, "size": [190, 80, 120], "sort": 80, "count": 1, "stacking": true, "turnover": false, "overhang_angle": 50, "stacking_limit": 0, "stacking_is_limited": false, "group_id": "030342E10"}, {"id": "09020Y1", "mass": 448, "size": [410, 240, 370], "sort": 81, "count": 1, "stacking": true, "turnover": false, "overhang_angle": 50, "stacking_limit": 0, "stacking_is_limited": false, "group_id": "440486S1"}, {"id": "09032Y1", "mass": 5194, "size": [360, 230, 100], "sort": 82, "count": 1, "stacking": true, "turnover": true, "overhang_angle": 50, "stacking_limit": 0, "stacking_is_limited": false, "group_id": "250193B5"}, {"id": "09079Y1", "mass": 404, "size": [130, 50, 80], "sort": 83, "count": 1, "stacking": true, "turnover": false, "overhang_angle": 50, "stacking_limit": 0, "stacking_is_limited": false, "group_id": "595919W6"}, {"id": "08130Y1", "mass": 2547, "size": [550, 140, 300], "sort": 84, "count": 7, "stacking": true, "turnover": false, "overhang_angle": 50, "stacking_limit": 0, "stacking_is_limited": false, "group_id": "1058549B9"}, {"id": "08093Y1", "mass": 586, "size": [170, 90, 60], "sort": 85, "count": 1, "stacking": true, "turnover": false, "overhang_angle": 50, "stacking_limit": 0, "stacking_is_limited": false, "group_id": "025875I10"}, {"id": "08027Y1", "mass": 1337, "size": [620, 510, 480], "sort": 86, "count": 1, "stacking": true, "turnover": false, "overhang_angle": 50, "stacking_limit": 0, "stacking_is_limited": false, "group_id": "390527U5"}, {"id": "08024Y1", "mass": 457, "size": [410, 240, 370], "sort": 87, "count": 1, "stacking": true, "turnover": false, "overhang_angle": 50, "stacking_limit": 0, "stacking_is_limited": false, "group_id": "8504101X10"}, {"id": "33037Y1", "mass": 2240, "size": [220, 161, 190], "sort": 88, "count": 1, "stacking": true, "turnover": false, "overhang_angle": 50, "stacking_limit": 0, "stacking_is_limited": false, "group_id": "10194100T9"}, {"id": "33086Y1", "mass": 1955, "size": [740, 148, 400], "sort": 89, "count": 1, "stacking": true, "turnover": false, "overhang_angle": 50, "stacking_limit": 0, "stacking_is_limited": false, "group_id": "759387Q2"}, {"id": "32013Y1", "mass": 254, "size": [260, 40, 100], "sort": 90, "count": 1, "stacking": true, "turnover": false, "overhang_angle": 50, "stacking_limit": 0, "stacking_is_limited": false, "group_id": "246613M2"}, {"id": "32017Y1", "mass": 250, "size": [160, 50, 80], "sort": 91, "count": 1, "stacking": true, "turnover": false, "overhang_angle": 50, "stacking_limit": 0, "stacking_is_limited": false, "group_id": "847694M1"}, {"id": "32043Y1", "mass": 262, "size": [190, 14, 90], "sort": 92, "count": 1, "stacking": true, "turnover": false, "overhang_angle": 50, "stacking_limit": 0, "stacking_is_limited": false, "group_id": "0421044S0"}, {"id": "32049Y1", "mass": 180, "size": [280, 30, 100], "sort": 93, "count": 1, "stacking": true, "turnover": false, "overhang_angle": 50, "stacking_limit": 0, "stacking_is_limited": false, "group_id": "222717T1"}, {"id": "31132Y1", "mass": 272, "size": [280, 90, 50], "sort": 94, "count": 1, "stacking": true, "turnover": false, "overhang_angle": 50, "stacking_limit": 0, "stacking_is_limited": false, "group_id": "02101012A10"}, {"id": "31130Y1", "mass": 176, "size": [260, 100, 50], "sort": 95, "count": 1, "stacking": true, "turnover": false, "overhang_angle": 50, "stacking_limit": 0, "stacking_is_limited": false, "group_id": "151757V2"}, {"id": "31128Y1", "mass": 257, "size": [280, 90, 50], "sort": 96, "count": 1, "stacking": true, "turnover": false, "overhang_angle": 50, "stacking_limit": 0, "stacking_is_limited": false, "group_id": "383165H6"}, {"id": "31126Y1", "mass": 218, "size": [450, 530, 230], "sort": 97, "count": 1, "stacking": true, "turnover": false, "overhang_angle": 50, "stacking_limit": 0, "stacking_is_limited": false, "group_id": "7109356W10"}, {"id": "31125Y1", "mass": 220, "size": [280, 90, 50], "sort": 98, "count": 1, "stacking": true, "turnover": false, "overhang_angle": 50, "stacking_limit": 0, "stacking_is_limited": false, "group_id": "3010863E8"}, {"id": "31123Y1", "mass": 200, "size": [285, 89, 46], "sort": 99, "count": 1, "stacking": true, "turnover": false, "overhang_angle": 50, "stacking_limit": 0, "stacking_is_limited": false, "group_id": "3438101F4"}, {"id": "31120Y1", "mass": 248, "size": [280, 90, 50], "sort": 100, "count": 1, "stacking": true, "turnover": false, "overhang_angle": 50, "stacking_limit": 0, "stacking_is_limited": false, "group_id": "7249810E2"}, {"id": "31119Y1", "mass": 200, "size": [250, 90, 40], "sort": 101, "count": 1, "stacking": true, "turnover": false, "overhang_angle": 50, "stacking_limit": 0, "stacking_is_limited": false, "group_id": "183005H2"}, {"id": "31115Y7", "mass": 25, "size": [160, 50, 80], "sort": 102, "count": 1, "stacking": true, "turnover": false, "overhang_angle": 50, "stacking_limit": 0, "stacking_is_limited": false, "group_id": "365980R3"}, {"id": "31113Y1", "mass": 264, "size": [280, 90, 50], "sort": 103, "count": 1, "stacking": true, "turnover": false, "overhang_angle": 50, "stacking_limit": 0, "stacking_is_limited": false, "group_id": "330394M9"}, {"id": "31110Y1", "mass": 240, "size": [280, 90, 50], "sort": 104, "count": 1, "stacking": true, "turnover": false, "overhang_angle": 50, "stacking_limit": 0, "stacking_is_limited": false, "group_id": "553934S3"}, {"id": "31109Y1", "mass": 219, "size": [400, 350, 270], "sort": 105, "count": 1, "stacking": true, "turnover": false, "overhang_angle": 50, "stacking_limit": 0, "stacking_is_limited": false, "group_id": "4971005O4"}, {"id": "31109Y7", "mass": 25, "size": [160, 50, 80], "sort": 106, "count": 1, "stacking": true, "turnover": false, "overhang_angle": 50, "stacking_limit": 0, "stacking_is_limited": false, "group_id": "64610100W9"}, {"id": "31105Y1", "mass": 217, "size": [260, 50, 90], "sort": 107, "count": 1, "stacking": true, "turnover": false, "overhang_angle": 50, "stacking_limit": 0, "stacking_is_limited": false, "group_id": "410510910V4"}, {"id": "31103Y1", "mass": 256, "size": [280, 90, 50], "sort": 108, "count": 1, "stacking": true, "turnover": false, "overhang_angle": 50, "stacking_limit": 0, "stacking_is_limited": false, "group_id": "033800S1"}, {"id": "31100Y1", "mass": 200, "size": [250, 90, 40], "sort": 109, "count": 1, "stacking": true, "turnover": false, "overhang_angle": 50, "stacking_limit": 0, "stacking_is_limited": false, "group_id": "467939W6"}, {"id": "31099Y7", "mass": 200, "size": [100, 280, 30], "sort": 110, "count": 1, "stacking": true, "turnover": false, "overhang_angle": 50, "stacking_limit": 0, "stacking_is_limited": false, "group_id": "862293I4"}, {"id": "31097Y1", "mass": 217, "size": [450, 530, 220], "sort": 111, "count": 1, "stacking": true, "turnover": false, "overhang_angle": 50, "stacking_limit": 0, "stacking_is_limited": false, "group_id": "6104309N8"}, {"id": "31090Y1", "mass": 220, "size": [280, 90, 50], "sort": 112, "count": 1, "stacking": true, "turnover": false, "overhang_angle": 50, "stacking_limit": 0, "stacking_is_limited": false, "group_id": "694462K4"}, {"id": "31080Y1", "mass": 250, "size": [260, 100, 40], "sort": 113, "count": 1, "stacking": true, "turnover": false, "overhang_angle": 50, "stacking_limit": 0, "stacking_is_limited": false, "group_id": "3431038Y5"}, {"id": "31075Y1", "mass": 287, "size": [280, 50, 110], "sort": 114, "count": 1, "stacking": true, "turnover": false, "overhang_angle": 50, "stacking_limit": 0, "stacking_is_limited": false, "group_id": "41010452Q0"}, {"id": "31072Y1", "mass": 222, "size": [250, 40, 90], "sort": 115, "count": 1, "stacking": true, "turnover": false, "overhang_angle": 50, "stacking_limit": 0, "stacking_is_limited": false, "group_id": "662638F2"}, {"id": "31071Y1", "mass": 160, "size": [280, 200, 100], "sort": 116, "count": 1, "stacking": true, "turnover": false, "overhang_angle": 50, "stacking_limit": 0, "stacking_is_limited": false, "group_id": "726728V0"}, {"id": "31070Y1", "mass": 280, "size": [280, 90, 50], "sort": 117, "count": 1, "stacking": true, "turnover": false, "overhang_angle": 50, "stacking_limit": 0, "stacking_is_limited": false, "group_id": "21030510J5"}, {"id": "31068Y1", "mass": 200, "size": [260, 100, 40], "sort": 118, "count": 1, "stacking": true, "turnover": false, "overhang_angle": 50, "stacking_limit": 0, "stacking_is_limited": false, "group_id": "127841P5"}, {"id": "31067Y1", "mass": 235, "size": [350, 260, 400], "sort": 119, "count": 1, "stacking": true, "turnover": false, "overhang_angle": 50, "stacking_limit": 0, "stacking_is_limited": false, "group_id": "9202104Z9"}, {"id": "31065Y1", "mass": 280, "size": [280, 90, 30], "sort": 120, "count": 1, "stacking": true, "turnover": false, "overhang_angle": 50, "stacking_limit": 0, "stacking_is_limited": false, "group_id": "559642Q6"}, {"id": "31062Y1", "mass": 300, "size": [280, 90, 30], "sort": 121, "count": 1, "stacking": true, "turnover": false, "overhang_angle": 50, "stacking_limit": 0, "stacking_is_limited": false, "group_id": "253674C2"}, {"id": "31044Y1", "mass": 257, "size": [260, 100, 40], "sort": 122, "count": 1, "stacking": true, "turnover": false, "overhang_angle": 50, "stacking_limit": 0, "stacking_is_limited": false, "group_id": "73310510L0"}, {"id": "31043Y1", "mass": 180, "size": [280, 100, 30], "sort": 123, "count": 1, "stacking": true, "turnover": false, "overhang_angle": 50, "stacking_limit": 0, "stacking_is_limited": false, "group_id": "2971019E10"}, {"id": "31037Y1", "mass": 280, "size": [260, 100, 40], "sort": 124, "count": 1, "stacking": true, "turnover": false, "overhang_angle": 50, "stacking_limit": 0, "stacking_is_limited": false, "group_id": "8105622X7"}, {"id": "31028Y1", "mass": 272, "size": [280, 90, 50], "sort": 125, "count": 1, "stacking": true, "turnover": false, "overhang_angle": 50, "stacking_limit": 0, "stacking_is_limited": false, "group_id": "23101010N10"}, {"id": "31023Y1", "mass": 166, "size": [130, 100, 60], "sort": 126, "count": 1, "stacking": true, "turnover": false, "overhang_angle": 50, "stacking_limit": 0, "stacking_is_limited": false, "group_id": "275608G2"}, {"id": "31021Y1", "mass": 150, "size": [100, 280, 30], "sort": 127, "count": 1, "stacking": true, "turnover": false, "overhang_angle": 50, "stacking_limit": 0, "stacking_is_limited": false, "group_id": "856529F5"}, {"id": "31019Y1", "mass": 240, "size": [260, 100, 40], "sort": 128, "count": 1, "stacking": true, "turnover": false, "overhang_angle": 50, "stacking_limit": 0, "stacking_is_limited": false, "group_id": "371647O1"}, {"id": "31018Y1", "mass": 220, "size": [250, 90, 40], "sort": 129, "count": 1, "stacking": true, "turnover": false, "overhang_angle": 50, "stacking_limit": 0, "stacking_is_limited": false, "group_id": "5981069G3"}, {"id": "31009Y1", "mass": 284, "size": [280, 90, 50], "sort": 130, "count": 1, "stacking": true, "turnover": false, "overhang_angle": 50, "stacking_limit": 0, "stacking_is_limited": false, "group_id": "255180B8"}], "timeout_params": {"timeout": 600}, "calculation_params": {"calculation_id": 430226, "accounting_center_of_mass": 0}}
