{"put_cargos": [], "cargo_space": {"id": 373900, "mass": 20, "size": [1250, 2100, 1800], "params": {"protrusion": [50, 50], "indentation": [50, 50]}, "carrying_capacity": 800}, "cargo_groups": [{"id": "29069Y1", "mass": 9300, "size": [260, 290, 190], "sort": 1, "count": 1, "stacking": true, "turnover": true, "overhang_angle": 50, "stacking_limit": 0, "stacking_is_limited": false, "group_id": "0937710J7"}, {"id": "29086Y1", "mass": 9331, "size": [280, 345, 190], "sort": 2, "count": 1, "stacking": true, "turnover": true, "overhang_angle": 50, "stacking_limit": 0, "stacking_is_limited": false, "group_id": "747140R9"}, {"id": "29110Y1", "mass": 12615, "size": [300, 342, 190], "sort": 3, "count": 1, "stacking": true, "turnover": true, "overhang_angle": 50, "stacking_limit": 0, "stacking_is_limited": false, "group_id": "0108532D5"}, {"id": "28128Y1", "mass": 10372, "size": [310, 323, 160], "sort": 4, "count": 2, "stacking": true, "turnover": false, "overhang_angle": 50, "stacking_limit": 0, "stacking_is_limited": false, "group_id": "9291210V10"}, {"id": "28122Y1", "mass": 9300, "size": [264, 332, 176], "sort": 5, "count": 1, "stacking": true, "turnover": false, "overhang_angle": 50, "stacking_limit": 0, "stacking_is_limited": false, "group_id": "10910732W4"}, {"id": "28105Y1", "mass": 10505, "size": [230, 340, 200], "sort": 6, "count": 1, "stacking": true, "turnover": false, "overhang_angle": 50, "stacking_limit": 0, "stacking_is_limited": false, "group_id": "323569K6"}, {"id": "28104Y1", "mass": 6231, "size": [270, 180, 200], "sort": 7, "count": 1, "stacking": true, "turnover": true, "overhang_angle": 50, "stacking_limit": 0, "stacking_is_limited": false, "group_id": "2105565X4"}, {"id": "28081Y1", "mass": 13056, "size": [250, 264, 240], "sort": 8, "count": 1, "stacking": true, "turnover": true, "overhang_angle": 50, "stacking_limit": 0, "stacking_is_limited": false, "group_id": "804442Y9"}, {"id": "28067Y1", "mass": 12411, "size": [370, 214, 200], "sort": 9, "count": 1, "stacking": true, "turnover": true, "overhang_angle": 50, "stacking_limit": 0, "stacking_is_limited": false, "group_id": "10991032H4"}, {"id": "28027Y1", "mass": 9436, "size": [280, 351, 190], "sort": 10, "count": 1, "stacking": true, "turnover": true, "overhang_angle": 50, "stacking_limit": 0, "stacking_is_limited": false, "group_id": "307320I5"}, {"id": "28016Y1", "mass": 12178, "size": [310, 332, 200], "sort": 11, "count": 1, "stacking": true, "turnover": true, "overhang_angle": 50, "stacking_limit": 0, "stacking_is_limited": false, "group_id": "51010822Z0"}, {"id": "28002Y1", "mass": 12267, "size": [310, 335, 200], "sort": 12, "count": 1, "stacking": true, "turnover": true, "overhang_angle": 50, "stacking_limit": 0, "stacking_is_limited": false, "group_id": "035923N5"}, {"id": "28001Y1", "mass": 12301, "size": [310, 336, 200], "sort": 13, "count": 1, "stacking": true, "turnover": true, "overhang_angle": 50, "stacking_limit": 0, "stacking_is_limited": false, "group_id": "152545D0"}, {"id": "27003Y1", "mass": 12246, "size": [310, 337, 200], "sort": 14, "count": 1, "stacking": true, "turnover": true, "overhang_angle": 50, "stacking_limit": 0, "stacking_is_limited": false, "group_id": "697887K7"}, {"id": "27012Y1", "mass": 9747, "size": [260, 314, 260], "sort": 15, "count": 1, "stacking": true, "turnover": true, "overhang_angle": 50, "stacking_limit": 0, "stacking_is_limited": false, "group_id": "729803W0"}, {"id": "27020Y1", "mass": 9384, "size": [270, 342, 180], "sort": 16, "count": 1, "stacking": true, "turnover": true, "overhang_angle": 50, "stacking_limit": 0, "stacking_is_limited": false, "group_id": "585914U6"}, {"id": "27021Y1", "mass": 9304, "size": [270, 337, 180], "sort": 17, "count": 1, "stacking": true, "turnover": true, "overhang_angle": 50, "stacking_limit": 0, "stacking_is_limited": false, "group_id": "636325X7"}, {"id": "27028Y1", "mass": 9105, "size": [250, 333, 170], "sort": 18, "count": 1, "stacking": true, "turnover": true, "overhang_angle": 50, "stacking_limit": 0, "stacking_is_limited": false, "group_id": "078705G1"}, {"id": "27052Y1", "mass": 9168, "size": [260, 327, 180], "sort": 19, "count": 1, "stacking": true, "turnover": true, "overhang_angle": 50, "stacking_limit": 0, "stacking_is_limited": false, "group_id": "5710767G9"}, {"id": "27054Y1", "mass": 4502, "size": [240, 197, 180], "sort": 20, "count": 1, "stacking": true, "turnover": true, "overhang_angle": 50, "stacking_limit": 0, "stacking_is_limited": false, "group_id": "8086510X3"}, {"id": "27069Y1", "mass": 9354, "size": [270, 329, 170], "sort": 21, "count": 1, "stacking": true, "turnover": true, "overhang_angle": 50, "stacking_limit": 0, "stacking_is_limited": false, "group_id": "557931G1"}, {"id": "27076Y1", "mass": 12571, "size": [310, 347, 210], "sort": 22, "count": 1, "stacking": true, "turnover": true, "overhang_angle": 50, "stacking_limit": 0, "stacking_is_limited": false, "group_id": "024373I0"}, {"id": "27080Y1", "mass": 12849, "size": [310, 337, 210], "sort": 23, "count": 1, "stacking": true, "turnover": true, "overhang_angle": 50, "stacking_limit": 0, "stacking_is_limited": false, "group_id": "688012V4"}, {"id": "27087Y1", "mass": 9479, "size": [300, 266, 210], "sort": 24, "count": 1, "stacking": true, "turnover": true, "overhang_angle": 50, "stacking_limit": 0, "stacking_is_limited": false, "group_id": "582820L10"}, {"id": "27102Y1", "mass": 6240, "size": [230, 280, 150], "sort": 25, "count": 1, "stacking": true, "turnover": true, "overhang_angle": 50, "stacking_limit": 0, "stacking_is_limited": false, "group_id": "1921042N7"}, {"id": "27115Y1", "mass": 1889, "size": [340, 69, 130], "sort": 26, "count": 1, "stacking": true, "turnover": false, "overhang_angle": 50, "stacking_limit": 0, "stacking_is_limited": false, "group_id": "345496J0"}, {"id": "26131Y1", "mass": 2025, "size": [170, 173, 110], "sort": 27, "count": 1, "stacking": true, "turnover": true, "overhang_angle": 50, "stacking_limit": 0, "stacking_is_limited": false, "group_id": "009094X1"}, {"id": "26124Y1", "mass": 12000, "size": [392, 235, 260], "sort": 28, "count": 1, "stacking": true, "turnover": false, "overhang_angle": 50, "stacking_limit": 0, "stacking_is_limited": false, "group_id": "941027U7"}, {"id": "26095Y1", "mass": 6240, "size": [260, 230, 190], "sort": 29, "count": 1, "stacking": true, "turnover": false, "overhang_angle": 50, "stacking_limit": 0, "stacking_is_limited": false, "group_id": "8103545D8"}, {"id": "26090Y1", "mass": 20555, "size": [400, 254, 270], "sort": 30, "count": 1, "stacking": true, "turnover": false, "overhang_angle": 50, "stacking_limit": 0, "stacking_is_limited": false, "group_id": "049110T8"}, {"id": "26079Y1", "mass": 6554, "size": [280, 172, 210], "sort": 31, "count": 1, "stacking": true, "turnover": true, "overhang_angle": 50, "stacking_limit": 0, "stacking_is_limited": false, "group_id": "7010745U8"}, {"id": "26005Y1", "mass": 10189, "size": [300, 340, 160], "sort": 32, "count": 2, "stacking": true, "turnover": false, "overhang_angle": 50, "stacking_limit": 0, "stacking_is_limited": false, "group_id": "383141J3"}, {"id": "26003Y1", "mass": 10139, "size": [310, 343, 140], "sort": 33, "count": 1, "stacking": true, "turnover": true, "overhang_angle": 50, "stacking_limit": 0, "stacking_is_limited": false, "group_id": "10910192T9"}, {"id": "25132Y1", "mass": 1362, "size": [170, 177, 120], "sort": 34, "count": 1, "stacking": true, "turnover": true, "overhang_angle": 50, "stacking_limit": 0, "stacking_is_limited": false, "group_id": "221847W6"}, {"id": "24123Y1", "mass": 4762, "size": [250, 159, 170], "sort": 35, "count": 1, "stacking": true, "turnover": true, "overhang_angle": 50, "stacking_limit": 0, "stacking_is_limited": false, "group_id": "198382B2"}, {"id": "24121Y1", "mass": 1985, "size": [390, 218, 200], "sort": 36, "count": 1, "stacking": true, "turnover": false, "overhang_angle": 50, "stacking_limit": 0, "stacking_is_limited": false, "group_id": "948943G10"}, {"id": "24094Y1", "mass": 1984, "size": [390, 218, 210], "sort": 37, "count": 1, "stacking": true, "turnover": false, "overhang_angle": 50, "stacking_limit": 0, "stacking_is_limited": false, "group_id": "243665S8"}, {"id": "24088Y1", "mass": 5214, "size": [290, 164, 200], "sort": 38, "count": 1, "stacking": true, "turnover": false, "overhang_angle": 50, "stacking_limit": 0, "stacking_is_limited": false, "group_id": "5442210U0"}, {"id": "24052Y1", "mass": 8211, "size": [300, 168, 200], "sort": 39, "count": 1, "stacking": true, "turnover": true, "overhang_angle": 50, "stacking_limit": 0, "stacking_is_limited": false, "group_id": "742299W1"}, {"id": "24049Y1", "mass": 5720, "size": [310, 143, 170], "sort": 40, "count": 1, "stacking": true, "turnover": true, "overhang_angle": 50, "stacking_limit": 0, "stacking_is_limited": false, "group_id": "1049939O7"}, {"id": "24044Y1", "mass": 4944, "size": [310, 97, 220], "sort": 41, "count": 1, "stacking": true, "turnover": true, "overhang_angle": 50, "stacking_limit": 0, "stacking_is_limited": false, "group_id": "449555B6"}, {"id": "24008Y1", "mass": 10095, "size": [360, 130, 270], "sort": 42, "count": 1, "stacking": true, "turnover": false, "overhang_angle": 50, "stacking_limit": 0, "stacking_is_limited": false, "group_id": "767292E4"}, {"id": "23021Y1", "mass": 4542, "size": [270, 130, 180], "sort": 43, "count": 1, "stacking": true, "turnover": true, "overhang_angle": 50, "stacking_limit": 0, "stacking_is_limited": false, "group_id": "46101043N5"}, {"id": "23085Y1", "mass": 2614, "size": [390, 144, 100], "sort": 44, "count": 1, "stacking": true, "turnover": false, "overhang_angle": 50, "stacking_limit": 0, "stacking_is_limited": false, "group_id": "600348O7"}, {"id": "23095Y1", "mass": 2452, "size": [400, 149, 100], "sort": 45, "count": 1, "stacking": true, "turnover": false, "overhang_angle": 50, "stacking_limit": 0, "stacking_is_limited": false, "group_id": "0659106B10"}, {"id": "23121Y1", "mass": 3612, "size": [350, 100, 130], "sort": 46, "count": 1, "stacking": true, "turnover": false, "overhang_angle": 50, "stacking_limit": 0, "stacking_is_limited": false, "group_id": "391097O0"}, {"id": "22113Y1", "mass": 2101, "size": [260, 209, 150], "sort": 47, "count": 1, "stacking": true, "turnover": false, "overhang_angle": 50, "stacking_limit": 0, "stacking_is_limited": false, "group_id": "937466Q9"}, {"id": "22090Y1", "mass": 7497, "size": [400, 247, 240], "sort": 48, "count": 1, "stacking": true, "turnover": false, "overhang_angle": 50, "stacking_limit": 0, "stacking_is_limited": false, "group_id": "394233Z2"}, {"id": "22038Y1", "mass": 2435, "size": [270, 166, 110], "sort": 49, "count": 1, "stacking": true, "turnover": false, "overhang_angle": 50, "stacking_limit": 0, "stacking_is_limited": false, "group_id": "7271007E1"}, {"id": "22030Y1", "mass": 2746, "size": [260, 210, 140], "sort": 50, "count": 1, "stacking": true, "turnover": false, "overhang_angle": 50, "stacking_limit": 0, "stacking_is_limited": false, "group_id": "728579F5"}, {"id": "22010Y1", "mass": 5432, "size": [350, 150, 140], "sort": 51, "count": 1, "stacking": true, "turnover": false, "overhang_angle": 50, "stacking_limit": 0, "stacking_is_limited": false, "group_id": "021744D5"}, {"id": "21010Y1", "mass": 10079, "size": [400, 160, 220], "sort": 52, "count": 1, "stacking": true, "turnover": false, "overhang_angle": 50, "stacking_limit": 0, "stacking_is_limited": false, "group_id": "082854H5"}, {"id": "21040Y1", "mass": 10941, "size": [380, 163, 240], "sort": 53, "count": 1, "stacking": true, "turnover": false, "overhang_angle": 50, "stacking_limit": 0, "stacking_is_limited": false, "group_id": "10975210X4"}, {"id": "20132Y1", "mass": 3365, "size": [390, 155, 240], "sort": 54, "count": 1, "stacking": true, "turnover": false, "overhang_angle": 50, "stacking_limit": 0, "stacking_is_limited": false, "group_id": "9828108Y8"}, {"id": "20093Y1", "mass": 9034, "size": [340, 156, 190], "sort": 55, "count": 1, "stacking": true, "turnover": false, "overhang_angle": 50, "stacking_limit": 0, "stacking_is_limited": false, "group_id": "6810700Q2"}, {"id": "20070Y1", "mass": 4800, "size": [410, 143, 180], "sort": 56, "count": 1, "stacking": true, "turnover": false, "overhang_angle": 50, "stacking_limit": 0, "stacking_is_limited": false, "group_id": "1034271K4"}, {"id": "20188Y1", "mass": 800, "size": [260, 140, 100], "sort": 57, "count": 1, "stacking": true, "turnover": false, "overhang_angle": 50, "stacking_limit": 0, "stacking_is_limited": false, "group_id": "9584510T6"}, {"id": "20005Y1", "mass": 5847, "size": [390, 173, 300], "sort": 58, "count": 1, "stacking": true, "turnover": false, "overhang_angle": 50, "stacking_limit": 0, "stacking_is_limited": false, "group_id": "127070Y6"}, {"id": "19007Y1", "mass": 3187, "size": [350, 205, 270], "sort": 59, "count": 1, "stacking": true, "turnover": false, "overhang_angle": 50, "stacking_limit": 0, "stacking_is_limited": false, "group_id": "492242S6"}, {"id": "19026Y1", "mass": 3310, "size": [410, 187, 210], "sort": 60, "count": 1, "stacking": true, "turnover": false, "overhang_angle": 50, "stacking_limit": 0, "stacking_is_limited": false, "group_id": "875599K3"}, {"id": "19036Y1", "mass": 3461, "size": [300, 95, 380], "sort": 61, "count": 1, "stacking": true, "turnover": false, "overhang_angle": 50, "stacking_limit": 0, "stacking_is_limited": false, "group_id": "659554B5"}, {"id": "19041Y1", "mass": 4003, "size": [330, 274, 260], "sort": 62, "count": 1, "stacking": true, "turnover": false, "overhang_angle": 50, "stacking_limit": 0, "stacking_is_limited": false, "group_id": "299573Y1"}, {"id": "19062Y1", "mass": 2338, "size": [410, 182, 400], "sort": 63, "count": 1, "stacking": true, "turnover": false, "overhang_angle": 50, "stacking_limit": 0, "stacking_is_limited": false, "group_id": "307224C4"}, {"id": "19083Y1", "mass": 2752, "size": [330, 215, 220], "sort": 64, "count": 1, "stacking": true, "turnover": false, "overhang_angle": 50, "stacking_limit": 0, "stacking_is_limited": false, "group_id": "7889510G1"}, {"id": "19093Y1", "mass": 1382, "size": [400, 164, 250], "sort": 65, "count": 1, "stacking": true, "turnover": false, "overhang_angle": 50, "stacking_limit": 0, "stacking_is_limited": false, "group_id": "632620S4"}, {"id": "18048Y1", "mass": 1359, "size": [200, 111, 150], "sort": 66, "count": 1, "stacking": true, "turnover": false, "overhang_angle": 50, "stacking_limit": 0, "stacking_is_limited": false, "group_id": "785704R3"}, {"id": "18040Y1", "mass": 3339, "size": [380, 155, 260], "sort": 67, "count": 1, "stacking": true, "turnover": true, "overhang_angle": 50, "stacking_limit": 0, "stacking_is_limited": false, "group_id": "003569A0"}, {"id": "18038Y1", "mass": 5202, "size": [400, 131, 200], "sort": 68, "count": 1, "stacking": true, "turnover": false, "overhang_angle": 50, "stacking_limit": 0, "stacking_is_limited": false, "group_id": "3243310D3"}, {"id": "18026Y1", "mass": 1898, "size": [310, 214, 230], "sort": 69, "count": 1, "stacking": true, "turnover": false, "overhang_angle": 50, "stacking_limit": 0, "stacking_is_limited": false, "group_id": "4410083D4"}, {"id": "18015Y1", "mass": 1884, "size": [400, 209, 170], "sort": 70, "count": 1, "stacking": true, "turnover": false, "overhang_angle": 50, "stacking_limit": 0, "stacking_is_limited": false, "group_id": "10617110W10"}, {"id": "17005Y1", "mass": 2000, "size": [290, 70, 190], "sort": 71, "count": 1, "stacking": true, "turnover": true, "overhang_angle": 50, "stacking_limit": 0, "stacking_is_limited": false, "group_id": "3057100H1"}, {"id": "17095Y1", "mass": 1327, "size": [220, 170, 270], "sort": 72, "count": 1, "stacking": true, "turnover": false, "overhang_angle": 50, "stacking_limit": 0, "stacking_is_limited": false, "group_id": "01098410B5"}, {"id": "17098Y1", "mass": 1981, "size": [200, 77, 190], "sort": 73, "count": 1, "stacking": true, "turnover": false, "overhang_angle": 50, "stacking_limit": 0, "stacking_is_limited": false, "group_id": "971150B5"}, {"id": "17126Y1", "mass": 7678, "size": [390, 267, 390], "sort": 74, "count": 1, "stacking": true, "turnover": false, "overhang_angle": 50, "stacking_limit": 0, "stacking_is_limited": false, "group_id": "2107086G6"}, {"id": "16053Y1", "mass": 2335, "size": [210, 159, 160], "sort": 75, "count": 1, "stacking": true, "turnover": false, "overhang_angle": 50, "stacking_limit": 0, "stacking_is_limited": false, "group_id": "668282U0"}, {"id": "16048Y1", "mass": 4716, "size": [310, 168, 220], "sort": 76, "count": 1, "stacking": true, "turnover": false, "overhang_angle": 50, "stacking_limit": 0, "stacking_is_limited": false, "group_id": "510420R1"}, {"id": "16040Y1", "mass": 2787, "size": [310, 250, 250], "sort": 77, "count": 1, "stacking": true, "turnover": false, "overhang_angle": 50, "stacking_limit": 0, "stacking_is_limited": false, "group_id": "406792P0"}, {"id": "15003Y1", "mass": 3981, "size": [270, 93, 200], "sort": 78, "count": 1, "stacking": true, "turnover": true, "overhang_angle": 50, "stacking_limit": 0, "stacking_is_limited": false, "group_id": "148432J6"}, {"id": "15142Y1", "mass": 2721, "size": [520, 232, 140], "sort": 79, "count": 1, "stacking": true, "turnover": false, "overhang_angle": 50, "stacking_limit": 0, "stacking_is_limited": false, "group_id": "2915103L9"}, {"id": "15071Y1", "mass": 2916, "size": [490, 222, 290], "sort": 80, "count": 1, "stacking": true, "turnover": true, "overhang_angle": 50, "stacking_limit": 0, "stacking_is_limited": false, "group_id": "710837G10"}, {"id": "15078Y1", "mass": 2893, "size": [500, 218, 290], "sort": 81, "count": 1, "stacking": true, "turnover": true, "overhang_angle": 50, "stacking_limit": 0, "stacking_is_limited": false, "group_id": "1079328X0"}, {"id": "14118Y1", "mass": 3387, "size": [330, 247, 120], "sort": 82, "count": 1, "stacking": true, "turnover": true, "overhang_angle": 50, "stacking_limit": 0, "stacking_is_limited": false, "group_id": "0004710F8"}, {"id": "14084Y1", "mass": 777, "size": [150, 176, 100], "sort": 83, "count": 1, "stacking": true, "turnover": true, "overhang_angle": 50, "stacking_limit": 0, "stacking_is_limited": false, "group_id": "7849106A7"}, {"id": "14046Y1", "mass": 2434, "size": [390, 157, 80], "sort": 84, "count": 2, "stacking": true, "turnover": true, "overhang_angle": 50, "stacking_limit": 0, "stacking_is_limited": false, "group_id": "8941063B10"}, {"id": "14013Y1", "mass": 799, "size": [150, 194, 100], "sort": 85, "count": 1, "stacking": true, "turnover": true, "overhang_angle": 50, "stacking_limit": 0, "stacking_is_limited": false, "group_id": "331170Y10"}, {"id": "13069Y1", "mass": 1631, "size": [490, 261, 310], "sort": 86, "count": 1, "stacking": true, "turnover": true, "overhang_angle": 50, "stacking_limit": 0, "stacking_is_limited": false, "group_id": "1028855Q2"}, {"id": "12007Y1", "mass": 1736, "size": [280, 108, 220], "sort": 87, "count": 1, "stacking": true, "turnover": false, "overhang_angle": 50, "stacking_limit": 0, "stacking_is_limited": false, "group_id": "604109I5"}, {"id": "12006Y1", "mass": 1540, "size": [380, 168, 110], "sort": 88, "count": 1, "stacking": true, "turnover": false, "overhang_angle": 50, "stacking_limit": 0, "stacking_is_limited": false, "group_id": "303405M10"}, {"id": "11001Y1", "mass": 1737, "size": [450, 173, 120], "sort": 89, "count": 1, "stacking": true, "turnover": true, "overhang_angle": 50, "stacking_limit": 0, "stacking_is_limited": false, "group_id": "7108138A1"}, {"id": "11009Y1", "mass": 2234, "size": [300, 165, 170], "sort": 90, "count": 1, "stacking": true, "turnover": false, "overhang_angle": 50, "stacking_limit": 0, "stacking_is_limited": false, "group_id": "6619810E9"}, {"id": "11068Y1", "mass": 818, "size": [230, 102, 140], "sort": 91, "count": 1, "stacking": true, "turnover": false, "overhang_angle": 50, "stacking_limit": 0, "stacking_is_limited": false, "group_id": "1068820V9"}, {"id": "11077Y1", "mass": 548, "size": [140, 163, 120], "sort": 92, "count": 1, "stacking": true, "turnover": false, "overhang_angle": 50, "stacking_limit": 0, "stacking_is_limited": false, "group_id": "678023P5"}, {"id": "11111Y1", "mass": 1562, "size": [310, 174, 130], "sort": 93, "count": 1, "stacking": true, "turnover": false, "overhang_angle": 50, "stacking_limit": 0, "stacking_is_limited": false, "group_id": "720831K2"}, {"id": "10088Y1", "mass": 2877, "size": [590, 200, 410], "sort": 94, "count": 1, "stacking": true, "turnover": false, "overhang_angle": 50, "stacking_limit": 0, "stacking_is_limited": false, "group_id": "6108174I2"}, {"id": "10053Y1", "mass": 1518, "size": [150, 170, 80], "sort": 95, "count": 1, "stacking": true, "turnover": false, "overhang_angle": 50, "stacking_limit": 0, "stacking_is_limited": false, "group_id": "705274X9"}, {"id": "09018Y1", "mass": 481, "size": [150, 40, 120], "sort": 96, "count": 1, "stacking": true, "turnover": false, "overhang_angle": 50, "stacking_limit": 0, "stacking_is_limited": false, "group_id": "9310771R5"}, {"id": "09028Y1", "mass": 580, "size": [180, 90, 60], "sort": 97, "count": 1, "stacking": true, "turnover": true, "overhang_angle": 50, "stacking_limit": 0, "stacking_is_limited": false, "group_id": "190249T2"}, {"id": "09076Y1", "mass": 1911, "size": [170, 80, 170], "sort": 98, "count": 1, "stacking": true, "turnover": false, "overhang_angle": 50, "stacking_limit": 0, "stacking_is_limited": false, "group_id": "349806J10"}, {"id": "08130Y1", "mass": 2547, "size": [550, 140, 300], "sort": 99, "count": 6, "stacking": true, "turnover": false, "overhang_angle": 50, "stacking_limit": 0, "stacking_is_limited": false, "group_id": "12510105H10"}, {"id": "33028Y1", "mass": 4534, "size": [390, 195, 210], "sort": 100, "count": 1, "stacking": true, "turnover": false, "overhang_angle": 50, "stacking_limit": 0, "stacking_is_limited": false, "group_id": "295409I5"}, {"id": "33046Y1", "mass": 4657, "size": [530, 173, 370], "sort": 101, "count": 1, "stacking": true, "turnover": false, "overhang_angle": 50, "stacking_limit": 0, "stacking_is_limited": false, "group_id": "5103164Z9"}, {"id": "33051Y1", "mass": 2259, "size": [390, 137, 300], "sort": 102, "count": 1, "stacking": true, "turnover": false, "overhang_angle": 50, "stacking_limit": 0, "stacking_is_limited": false, "group_id": "580000O5"}, {"id": "33056Y1", "mass": 4564, "size": [310, 310, 180], "sort": 103, "count": 1, "stacking": true, "turnover": false, "overhang_angle": 50, "stacking_limit": 0, "stacking_is_limited": false, "group_id": "7951072H9"}, {"id": "33058Y1", "mass": 5126, "size": [590, 181, 420], "sort": 104, "count": 1, "stacking": true, "turnover": false, "overhang_angle": 50, "stacking_limit": 0, "stacking_is_limited": false, "group_id": "4291006Y6"}, {"id": "33070Y1", "mass": 2208, "size": [440, 272, 150], "sort": 105, "count": 1, "stacking": true, "turnover": false, "overhang_angle": 50, "stacking_limit": 0, "stacking_is_limited": false, "group_id": "0607106D3"}, {"id": "33093Y1", "mass": 1478, "size": [410, 129, 310], "sort": 106, "count": 1, "stacking": true, "turnover": false, "overhang_angle": 50, "stacking_limit": 0, "stacking_is_limited": false, "group_id": "0898100D4"}, {"id": "33100Y1", "mass": 1900, "size": [400, 132, 300], "sort": 107, "count": 1, "stacking": true, "turnover": false, "overhang_angle": 50, "stacking_limit": 0, "stacking_is_limited": false, "group_id": "1961610H3"}, {"id": "33102Y1", "mass": 2307, "size": [390, 163, 300], "sort": 108, "count": 1, "stacking": true, "turnover": false, "overhang_angle": 50, "stacking_limit": 0, "stacking_is_limited": false, "group_id": "6102483O7"}, {"id": "33103Y1", "mass": 4000, "size": [260, 90, 190], "sort": 109, "count": 2, "stacking": true, "turnover": false, "overhang_angle": 50, "stacking_limit": 0, "stacking_is_limited": false, "group_id": "231523X1"}, {"id": "33116Y1", "mass": 1536, "size": [385, 250, 295], "sort": 110, "count": 1, "stacking": true, "turnover": false, "overhang_angle": 50, "stacking_limit": 0, "stacking_is_limited": false, "group_id": "317576Q8"}, {"id": "33122Y1", "mass": 400, "size": [600, 30, 30], "sort": 111, "count": 1, "stacking": true, "turnover": false, "overhang_angle": 50, "stacking_limit": 0, "stacking_is_limited": false, "group_id": "2891085C0"}, {"id": "32029Y1", "mass": 125, "size": [420, 38, 300], "sort": 112, "count": 1, "stacking": true, "turnover": false, "overhang_angle": 50, "stacking_limit": 0, "stacking_is_limited": false, "group_id": "4101102F7"}, {"id": "32043Y1", "mass": 262, "size": [190, 14, 90], "sort": 113, "count": 1, "stacking": true, "turnover": false, "overhang_angle": 50, "stacking_limit": 0, "stacking_is_limited": false, "group_id": "5109344U8"}, {"id": "32089Y1", "mass": 2240, "size": [220, 161, 190], "sort": 114, "count": 1, "stacking": true, "turnover": true, "overhang_angle": 50, "stacking_limit": 0, "stacking_is_limited": false, "group_id": "757259E7"}], "timeout_params": {"timeout": 600}, "calculation_params": {"calculation_id": 523678, "accounting_center_of_mass": 0}}
